{"assets":{"5D93E7FD8D7F559CEBA7C6730248047C":{"type":"texture","index":0,"assetRequest":{"type":"slide","state":"contents","slide":"none"},"url":{"native":"assets\/CD609B82-2A23-47E2-9FC1-8D7DDC1B213A.pdf"},"width":1024,"height":768},"73C4A150A4C7B972B3DD683F1C2B2AC2":{"type":"texture","index":1,"assetRequest":{"type":"slide","state":"contents","slide":"none"},"url":{"native":"assets\/CD609B82-2A23-47E2-9FC1-8D7DDC1B213A.pdf"},"width":1024,"height":768}},"events":[{"effects":[{"beginTime":0,"baseLayer":{"animations":[],"initialState":{"affineTransform":[1,0,0,1,0,0],"masksToBounds":false,"rotation":0,"scale":1,"position":{"pointX":512,"pointY":384},"width":1024,"sublayerTransform":[1,0,0,0,0,1,0,0,0,0,1,0,0,0,0,1],"contentsRect":{"y":0,"x":0,"width":1,"height":1},"opacity":1,"edgeAntialiasingMask":251658240,"height":768,"hidden":false,"anchorPoint":{"pointX":0.5,"pointY":0.5}},"objectID":"0","layers":[{"animations":[],"initialState":{"affineTransform":[1,0,0,1,0,0],"masksToBounds":false,"rotation":0,"scale":1,"position":{"pointX":512,"pointY":384},"width":1024,"sublayerTransform":[1,0,0,0,0,1,0,0,0,0,1,-0.00049229876906403734,0,0,0,1],"contentsRect":{"y":0,"x":0,"width":1,"height":1},"opacity":1,"edgeAntialiasingMask":251658240,"height":768,"hidden":false,"anchorPoint":{"pointX":0.5,"pointY":0.5}},"layers":[{"animations":[],"layers":[],"texturedRectangle":{"isBackgroundTexture":false,"singleTextureOpacity":1,"textureType":0,"textBaseline":0,"textXHeight":0,"isVerticalText":false},"initialState":{"affineTransform":[1,0,0,1,0,0],"masksToBounds":false,"rotation":0,"scale":1,"position":{"pointX":512,"pointY":384},"width":1024,"sublayerTransform":[1,0,0,0,0,1,0,0,0,0,1,0,0,0,0,1],"contentsRect":{"y":0,"x":0,"width":1,"height":1},"opacity":1,"edgeAntialiasingMask":0,"height":768,"hidden":false,"anchorPoint":{"pointX":0.5,"pointY":0.5}},"texture":"73C4A150A4C7B972B3DD683F1C2B2AC2"},{"animations":[{"timeOffset":0,"from":{"scalar":false},"beginTime":0,"repeatCount":0,"fillMode":"both","property":"hidden","autoreverses":false,"duration":0.01,"to":{"scalar":true}}],"layers":[],"texturedRectangle":{"isBackgroundTexture":false,"singleTextureOpacity":1,"textureType":0,"textBaseline":0,"textXHeight":0,"isVerticalText":false},"initialState":{"affineTransform":[1,0,0,1,0,0],"masksToBounds":false,"rotation":0,"scale":1,"position":{"pointX":512,"pointY":384},"width":1024,"sublayerTransform":[1,0,0,0,0,1,0,0,0,0,1,0,0,0,0,1],"contentsRect":{"y":0,"x":0,"width":1,"height":1},"opacity":1,"edgeAntialiasingMask":0,"height":768,"hidden":false,"anchorPoint":{"pointX":0.5,"pointY":0.5}},"texture":"5D93E7FD8D7F559CEBA7C6730248047C"}]}]},"effects":[],"duration":0.01,"type":"transition","name":"none","objectID":"0"}],"automaticPlay":false,"hyperlinks":[],"accessibility":[{"text":"Factory methods + default arguments","targetRectangle":{"y":90,"x":39.2919921875,"width":945.416015625,"height":53}},{"text":"fun createPresenter(","targetRectangle":{"y":198.99999332427979,"x":14.206043243408203,"width":337.1484375,"height":33}},{"text":"        router: Router = this.router,","targetRectangle":{"y":231.99999332427979,"x":14.206043243408203,"width":623.724609375,"height":33}},{"text":"        signUpView: SignUpView = this.signUpView,","targetRectangle":{"y":264.99999332427979,"x":14.206043243408203,"width":826.013671875,"height":33}},{"text":"        userProvider: UserProvider = this.userProvider,","targetRectangle":{"y":297.99999332427979,"x":14.206043243408203,"width":927.158203125,"height":33}},{"text":"        formValidator: FormValidator = this.formValidator,","targetRectangle":{"y":330.99999332427979,"x":14.206043243408203,"width":977.73046875,"height":33}},{"text":"        signUpUseCase: SignUpUseCase = this.signUpUseCase","targetRectangle":{"y":363.99999332427979,"x":14.206043243408203,"width":960.873046875,"height":33}},{"text":"): SignUpPresenter {","targetRectangle":{"y":396.99999332427979,"x":14.206043243408203,"width":337.1484375,"height":33}},{"text":"    return SignUpPresenter(","targetRectangle":{"y":429.99999332427979,"x":14.206043243408203,"width":455.150390625,"height":33}},{"text":"            signUpView,","targetRectangle":{"y":462.99999332427979,"x":14.206043243408203,"width":387.720703125,"height":33}},{"text":"            router,","targetRectangle":{"y":495.99999332427979,"x":14.206043243408203,"width":320.291015625,"height":33}},{"text":"            formValidator,","targetRectangle":{"y":528.99999332427979,"x":14.206043243408203,"width":438.29296875,"height":33}},{"text":"            userProvider,","targetRectangle":{"y":561.99999332427979,"x":14.206043243408203,"width":421.435546875,"height":33}},{"text":"            signUpUseCase","targetRectangle":{"y":594.99999332427979,"x":14.206043243408203,"width":421.435546875,"height":33}},{"text":"    )","targetRectangle":{"y":627.99999332427979,"x":14.206043243408203,"width":84.287109375,"height":33}},{"text":"}","targetRectangle":{"y":660.99999332427979,"x":14.206043243408203,"width":16.857421875,"height":33}},{"text":"￼","targetRectangle":{"y":733.99999988079071,"x":502.4999994635582,"width":18,"height":20}}],"baseLayer":{"animations":[],"initialState":{"affineTransform":[1,0,0,1,0,0],"masksToBounds":false,"rotation":0,"scale":1,"position":{"pointX":512,"pointY":384},"width":1024,"sublayerTransform":[1,0,0,0,0,1,0,0,0,0,1,0,0,0,0,1],"contentsRect":{"y":0,"x":0,"width":1,"height":1},"opacity":1,"edgeAntialiasingMask":251658240,"height":768,"hidden":false,"anchorPoint":{"pointX":0.5,"pointY":0.5}},"objectID":"0","layers":[{"animations":[],"initialState":{"affineTransform":[1,0,0,1,0,0],"masksToBounds":false,"rotation":0,"scale":1,"position":{"pointX":512,"pointY":384},"width":1024,"sublayerTransform":[1,0,0,0,0,1,0,0,0,0,1,-0.00049229876906403734,0,0,0,1],"contentsRect":{"y":0,"x":0,"width":1,"height":1},"opacity":1,"edgeAntialiasingMask":251658240,"height":768,"hidden":false,"anchorPoint":{"pointX":0.5,"pointY":0.5}},"layers":[{"animations":[],"layers":[],"texturedRectangle":{"isBackgroundTexture":false,"singleTextureOpacity":1,"textureType":0,"textBaseline":0,"textXHeight":0,"isVerticalText":false},"initialState":{"affineTransform":[1,0,0,1,0,0],"masksToBounds":false,"rotation":0,"scale":1,"position":{"pointX":512,"pointY":384},"width":1024,"sublayerTransform":[1,0,0,0,0,1,0,0,0,0,1,0,0,0,0,1],"contentsRect":{"y":0,"x":0,"width":1,"height":1},"opacity":1,"edgeAntialiasingMask":0,"height":768,"hidden":false,"anchorPoint":{"pointX":0.5,"pointY":0.5}},"texture":"5D93E7FD8D7F559CEBA7C6730248047C"}]}]}}]}